ntp/__init__.py
ntp-1.0.0a1.dist-info/METADATA
ntp-1.0.0a1.dist-info/WHEEL
ntp-1.0.0a1.dist-info/top_level.txt
ntp-1.0.0a1.dist-info/RECORD
