Metadata-Version: 1.2
Name: ntp
Version: 1.0.0a1
Summary: GCPDS: ntp
Home-page: UNKNOWN
Author: Yeison Cardona
Author-email: yencardonaal@unal.edu.com
Maintainer: Yeison Cardona
Maintainer-email: yencardonaal@unal.edu.com
License: BSD License
Download-URL: https://bitbucket.org/gcpds/python-ntp
Platform: UNKNOWN
